mysql_kernel/__init__.py
mysql_kernel/__main__.py
mysql_kernel/install.py
mysql_kernel/kernel.py
mysql_kernel-0.4.1.dist-info/LICENSE.txt
mysql_kernel-0.4.1.dist-info/METADATA
mysql_kernel-0.4.1.dist-info/WHEEL
mysql_kernel-0.4.1.dist-info/top_level.txt
mysql_kernel-0.4.1.dist-info/RECORD
