Metadata-Version: 2.1
Name: mysql-kernel
Version: 0.4.1
Summary: A mysql kernel for Jupyter.
Home-page: https://github.com/Hourout/mysql_kernel
Author: JinQing Lee
Author-email: hourout@163.com
License: Apache License Version 2.0
Keywords: jupyter_kernel,mysql_kernel
Platform: UNKNOWN
Classifier: Framework :: IPython
Classifier: License :: OSI Approved :: Apache Software License
Classifier: Programming Language :: Python :: 3.6
Classifier: Programming Language :: Python :: 3.7
Classifier: Programming Language :: Python :: 3.8
Classifier: Programming Language :: Python :: 3.9
Classifier: Intended Audience :: Developers
Classifier: Intended Audience :: Education
Classifier: Intended Audience :: Science/Research
Classifier: Topic :: Scientific/Engineering
Classifier: Topic :: System :: Shells
Requires-Dist: pymysql
Requires-Dist: sqlalchemy
Requires-Dist: pandas
Requires-Dist: jupyter
